README.rst
setup.py
crawl_zillow/__init__.py
crawl_zillow/helpers.py
crawl_zillow/htmlparser.py
crawl_zillow/urlencoder.py
crawl_zillow/zzz_manual_install.py
crawl_zillow.egg-info/PKG-INFO
crawl_zillow.egg-info/SOURCES.txt
crawl_zillow.egg-info/dependency_links.txt
crawl_zillow.egg-info/requires.txt
crawl_zillow.egg-info/top_level.txt
crawl_zillow/packages/__init__.py
crawl_zillow/packages/crawlib/__init__.py
crawl_zillow/packages/crawlib/decoder.py
crawl_zillow/packages/crawlib/exc.py
crawl_zillow/packages/crawlib/helpers.py
crawl_zillow/packages/crawlib/htmlparser.py
crawl_zillow/packages/crawlib/spider.py
crawl_zillow/packages/crawlib/urlencoder.py
crawl_zillow/packages/crawlib/zzz_manual_install.py